realsense_recorder/__init__.py
realsense_recorder/__main__.py
realsense_recorder/cmd/__init__.py
realsense_recorder/cmd/calibrate.py
realsense_recorder/cmd/post_process.py
realsense_recorder/cmd/serve.py
realsense_recorder/common/__init__.py
realsense_recorder/common/config.py
realsense_recorder/common/interaction.py
realsense_recorder/common/record.py
realsense_recorder/common/utils.py
realsense_recorder/filters/__init__.py
realsense_recorder/io/Compression.py
realsense_recorder/io/DirectoryReader.py
realsense_recorder/io/Sequence.py
realsense_recorder/io/Sync.py
realsense_recorder/io/__init__.py
realsense_recorder/scripts/__init__.py
realsense_recorder/scripts/configure.py
markit_realsense_recorder-1.8.2.dist-info/METADATA
markit_realsense_recorder-1.8.2.dist-info/WHEEL
markit_realsense_recorder-1.8.2.dist-info/top_level.txt
markit_realsense_recorder-1.8.2.dist-info/RECORD
